{"title":"about","type":"page","uid":"03933793d01427bd4ef056d0a9b02560","text":"Who I Am这里是sasigi的个人博客,立志于打造最优秀的产品,成为一名既优雅而有深度的技术人才,欢迎大家来做技术交流。 ✨Skills &amp; Tools-技能 &amp; 工具📜Experiences-经验🏆Achievements-成就🔭Working on-项目...","date":"2023-11-05T06:11:45.000Z","updated":"2023-11-05T06:26:48.399Z","comments":true,"path":"api/pages/about/index.json","covers":null,"excerpt":"","content":"<h2 id=\"Who-I-Am\"><a href=\"#Who-I-Am\" class=\"headerlink\" title=\"Who I Am\"></a>Who I Am</h2><p>这里是sasigi的个人博客,立志于打造最优秀的产品,成为一名既优雅而有深度的技术人才,欢迎大家来做技术交流。</p>\n<h2 id=\"✨Skills-Tools-技能-工具\"><a href=\"#✨Skills-Tools-技能-工具\" class=\"headerlink\" title=\"✨Skills &amp; Tools-技能 &amp; 工具\"></a>✨Skills &amp; Tools-技能 &amp; 工具</h2><h2 id=\"📜Experiences-经验\"><a href=\"#📜Experiences-经验\" class=\"headerlink\" title=\"📜Experiences-经验\"></a>📜Experiences-经验</h2><h2 id=\"🏆Achievements-成就\"><a href=\"#🏆Achievements-成就\" class=\"headerlink\" title=\"🏆Achievements-成就\"></a>🏆Achievements-成就</h2><h2 id=\"🔭Working-on-项目\"><a href=\"#🔭Working-on-项目\" class=\"headerlink\" title=\"🔭Working on-项目\"></a>🔭Working on-项目</h2><h2 id=\"✍🏻My-blogs-博客\"><a href=\"#✍🏻My-blogs-博客\" class=\"headerlink\" title=\"✍🏻My blogs-博客\"></a>✍🏻My blogs-博客</h2>","count_time":{"symbolsCount":157,"symbolsTime":"1 mins."},"toc":"<ol class=\"toc\"><li class=\"toc-item toc-level-2\"><a class=\"toc-link\" href=\"#Who-I-Am\"><span class=\"toc-text\">Who I Am</span></a></li><li class=\"toc-item toc-level-2\"><a class=\"toc-link\" href=\"#%E2%9C%A8Skills-Tools-%E6%8A%80%E8%83%BD-%E5%B7%A5%E5%85%B7\"><span class=\"toc-text\">✨Skills &amp; Tools-技能 &amp; 工具</span></a></li><li class=\"toc-item toc-level-2\"><a class=\"toc-link\" href=\"#%F0%9F%93%9CExperiences-%E7%BB%8F%E9%AA%8C\"><span class=\"toc-text\">📜Experiences-经验</span></a></li><li class=\"toc-item toc-level-2\"><a class=\"toc-link\" href=\"#%F0%9F%8F%86Achievements-%E6%88%90%E5%B0%B1\"><span class=\"toc-text\">🏆Achievements-成就</span></a></li><li class=\"toc-item toc-level-2\"><a class=\"toc-link\" href=\"#%F0%9F%94%ADWorking-on-%E9%A1%B9%E7%9B%AE\"><span class=\"toc-text\">🔭Working on-项目</span></a></li><li class=\"toc-item toc-level-2\"><a class=\"toc-link\" href=\"#%E2%9C%8D%F0%9F%8F%BBMy-blogs-%E5%8D%9A%E5%AE%A2\"><span class=\"toc-text\">✍🏻My blogs-博客</span></a></li></ol>","data":[]}